sphinxcontrib_traceability-0.1.4-py3.7-nspkg.pth
sphinxcontrib/traceability.py
sphinxcontrib_traceability-0.1.4.dist-info/LICENSE
sphinxcontrib_traceability-0.1.4.dist-info/METADATA
sphinxcontrib_traceability-0.1.4.dist-info/WHEEL
sphinxcontrib_traceability-0.1.4.dist-info/namespace_packages.txt
sphinxcontrib_traceability-0.1.4.dist-info/top_level.txt
sphinxcontrib_traceability-0.1.4.dist-info/RECORD
