Metadata-Version: 2.1
Name: sphinxcontrib-traceability
Version: 0.1.4
Summary: Sphinx traceability extension
Home-page: https://github.com/ociu/sphinx-traceability-extension
Author: Oscar Ciudad
Author-email: oscar@jacho.net
License: GNU General Public License v3 (GPLv3)
Download-URL: https://github.com/ociu/sphinx-traceability-extension/archive/v0.1.4.tar.gz
Keywords: traceability,requirements engineering,requirements management,software engineering,systems engineering,sphinx,requirements
Platform: any
Classifier: Development Status :: 5 - Production/Stable
Classifier: Environment :: Console
Classifier: Environment :: Web Environment
Classifier: Framework :: Sphinx :: Extension
Classifier: Intended Audience :: Developers
Classifier: License :: OSI Approved :: GNU General Public License v3 (GPLv3)
Classifier: Operating System :: OS Independent
Classifier: Programming Language :: Python
Classifier: Programming Language :: Python :: 2.6
Classifier: Programming Language :: Python :: 2.7
Classifier: Programming Language :: Python :: 3.2
Classifier: Programming Language :: Python :: 3.3
Classifier: Programming Language :: Python :: 3.4
Classifier: Programming Language :: Python :: 3.5
Classifier: Topic :: Documentation
Classifier: Topic :: Documentation :: Sphinx
Classifier: Topic :: Utilities
Requires-Dist: Sphinx (>=0.6)
